saucypy/__init__.py
saucypy/saucypy.py
saucypy-0.6.data/scripts/saucypy.py
saucypy-0.6.dist-info/DESCRIPTION.rst
saucypy-0.6.dist-info/METADATA
saucypy-0.6.dist-info/RECORD
saucypy-0.6.dist-info/WHEEL
saucypy-0.6.dist-info/metadata.json
saucypy-0.6.dist-info/top_level.txt
