Metadata-Version: 2.0
Name: saucypy
Version: 0.6
Summary: SauceLabs API Python Wrapper
Home-page: https://github.com/Neko-Design/saucypy
Author: Ewen McCahon
Author-email: ewen.m.mccahon@student.uts.edu.au
License: Apache License, Version 2.0
Download-URL: https://github.com/Neko-Design/saucypy/tarball/0.6
Keywords: saucelabs,api,wrapper,interface,sauce
Platform: UNKNOWN
Classifier: Programming Language :: Python :: 2.7
Requires-Dist: requests
